menagerie/Settings.py
menagerie/SiteGen.py
menagerie/__init__.py
menagerie/__main__.py
menagerie/generate.py
menagerie/new_project.py
menagerie/Items/AbstractItem.py
menagerie/Items/MinifiedItemMixin.py
menagerie/Items/__init__.py
menagerie/Items/Managers/AbstractManager.py
menagerie/Items/Managers/MetaManager.py
menagerie/Items/Managers/PageManager.py
menagerie/Items/Managers/StaticManager.py
menagerie/Items/Managers/__init__.py
menagerie/Items/Meta/CSSMetaItem.py
menagerie/Items/Meta/JSMetaItem.py
menagerie/Items/Meta/JSONMetaItem.py
menagerie/Items/Meta/MetaItem.py
menagerie/Items/Meta/XMLMetaItem.py
menagerie/Items/Meta/__init__.py
menagerie/Items/Pages/AbstractPage.py
menagerie/Items/Pages/HTMLPage.py
menagerie/Items/Pages/MDPage.py
menagerie/Items/Pages/__init__.py
menagerie/Items/Pages/Schema/JSONSchema.py
menagerie/Items/Pages/Schema/XMLSchema.py
menagerie/Items/Pages/Schema/__init__.py
menagerie/Items/Static/StaticCSS.py
menagerie/Items/Static/StaticImage.py
menagerie/Items/Static/StaticItem.py
menagerie/Items/Static/StaticJS.py
menagerie/Items/Static/StaticSCSS.py
menagerie/Items/Static/__init__.py
menagerie/base_templates/__init__.py
menagerie/base_templates/meta.jinja2
menagerie/base_templates/page_base.jinja2
menagerie/base_templates/meta_files/__init__.py
menagerie/base_templates/meta_files/base.js
menagerie/base_templates/meta_files/browserconfig.jinja2
menagerie/base_templates/meta_files/manifest.jinja2
menagerie/base_templates/meta_files/robots.jinja2
menagerie/base_templates/meta_files/schema.css
menagerie/base_templates/meta_files/schema.js
menagerie/base_templates/meta_files/sitemap.jinja2
menagerie/base_templates/schema_templates/__init__.py
menagerie/base_templates/schema_templates/schema_macros.jinja2
menagerie/base_templates/schema_templates/schema_template.jinja2
menagerie/base_templates/schema_templates/xml_schema.jinja2
menagerie/base_templates/schema_templates/json/__init__.py
menagerie_docs-0.1.14.dist-info/LICENSE
menagerie_docs-0.1.14.dist-info/METADATA
menagerie_docs-0.1.14.dist-info/WHEEL
menagerie_docs-0.1.14.dist-info/entry_points.txt
menagerie_docs-0.1.14.dist-info/top_level.txt
menagerie_docs-0.1.14.dist-info/RECORD
