Metadata-Version: 2.1
Name: menagerie-docs
Version: 0.1.14
Summary: A static site generator made for MarkDown, HTML, JsonSchema, XMLSchema, and more
Home-page: https://github.com/Bwc9876/menagerie
Author: bwc9876
Author-email: bwc9876@gmail.com
License: GNU Lesser General Public License v2.1
Classifier: License :: OSI Approved :: GNU Lesser General Public License v2 or later (LGPLv2+)
Classifier: Development Status :: 2 - Pre-Alpha
Classifier: Intended Audience :: Developers
Classifier: Environment :: Console
Classifier: Programming Language :: Python :: 3.10
Classifier: Natural Language :: English
License-File: LICENSE
Requires-Dist: jinja2
Requires-Dist: json-schema-for-humans
Requires-Dist: xmlschema
Requires-Dist: htmlmin
Requires-Dist: rjsmin
Requires-Dist: rcssmin
Requires-Dist: pillow
Requires-Dist: jsonschema
Requires-Dist: markdown2
Requires-Dist: markdown (==3.3.4)
Requires-Dist: ndicts
Requires-Dist: json-minify
Requires-Dist: beautifulsoup4
Requires-Dist: pyyaml
Requires-Dist: libsass
